nbaflow/__init__.py
nbaflow/players.py
nbaflow/utils/__init__.py
nbaflow/utils/log.py
nbaflow/utils/requests.py
tests/__init__.py
tests/conftest.py
tests/test_players.py
tests/test_utils_log.py
nbaflow-0.1.1.dist-info/LICENSE
nbaflow-0.1.1.dist-info/METADATA
nbaflow-0.1.1.dist-info/WHEEL
nbaflow-0.1.1.dist-info/top_level.txt
nbaflow-0.1.1.dist-info/RECORD
